DataGateway/__init__.py
DataGateway/src.py
datagateway-0.2.0.dist-info/METADATA
datagateway-0.2.0.dist-info/WHEEL
datagateway-0.2.0.dist-info/top_level.txt
datagateway-0.2.0.dist-info/RECORD
