Metadata-Version: 2.4
Name: DataGateway
Version: 0.2.0
Summary: A Python interface for managing Parquet tables stored on Google Drive.
Author-email: Jason <jason.wang1709@gmail.com>
License: MIT
Classifier: Programming Language :: Python :: 3
Classifier: Programming Language :: Python :: 3.10
Classifier: Operating System :: OS Independent
Classifier: License :: OSI Approved :: MIT License
Requires-Python: >=3.10
Requires-Dist: pandas
Requires-Dist: pyarrow
Requires-Dist: pydrive2
